sfmanager/__init__.py
sfmanager/app.py
sfmanager/utils.py
sfmanager-0.1.13.dist-info/METADATA
sfmanager-0.1.13.dist-info/WHEEL
sfmanager-0.1.13.dist-info/entry_points.txt
sfmanager-0.1.13.dist-info/licenses/LICENSE
sfmanager-0.1.13.dist-info/RECORD
