Metadata-Version: 2.4
Name: sfmanager
Version: 0.1.13
Summary: This library is not that useful. Perhaps someday it will become great.
Project-URL: Homepage, https://github.com/GrandTheBest/sfmanager
Project-URL: Issues, https://github.com/GrandTheBest/sfmanager/issues
Author-email: GrandTheBest <grandinfocm@gmail.com>
License-File: LICENSE
Classifier: License :: OSI Approved :: GNU General Public License v3 or later (GPLv3+)
Classifier: Operating System :: OS Independent
Classifier: Programming Language :: Python :: 3
Requires-Python: >=3.10.0
Requires-Dist: httpx
Requires-Dist: loguru>=0.7.2
Requires-Dist: pillow>=9.0.1
